odoo/addons/ssi_school/README.rst
odoo/addons/ssi_school/__init__.py
odoo/addons/ssi_school/__manifest__.py
odoo/addons/ssi_school/menu.xml
odoo/addons/ssi_school/approval_template/school_class.xml
odoo/addons/ssi_school/approval_template/school_curiculum.xml
odoo/addons/ssi_school/approval_template/school_enrollment.xml
odoo/addons/ssi_school/approval_template/school_homeroom.xml
odoo/addons/ssi_school/approval_template/school_report_card.xml
odoo/addons/ssi_school/approval_template/school_student_score_sheet.xml
odoo/addons/ssi_school/demo/res_partner.xml
odoo/addons/ssi_school/demo/school_academic_term.xml
odoo/addons/ssi_school/demo/school_academic_year.xml
odoo/addons/ssi_school/demo/school_curiculum.xml
odoo/addons/ssi_school/demo/school_grade.xml
odoo/addons/ssi_school/demo/school_grade_type.xml
odoo/addons/ssi_school/demo/school_pass_criteria.xml
odoo/addons/ssi_school/demo/school_score_type.xml
odoo/addons/ssi_school/demo/school_scoring_system.xml
odoo/addons/ssi_school/demo/school_student.xml
odoo/addons/ssi_school/demo/school_subject.xml
odoo/addons/ssi_school/demo/school_teacher.xml
odoo/addons/ssi_school/ir_sequence/school_class.xml
odoo/addons/ssi_school/ir_sequence/school_curiculum.xml
odoo/addons/ssi_school/ir_sequence/school_enrollment.xml
odoo/addons/ssi_school/ir_sequence/school_homeroom.xml
odoo/addons/ssi_school/ir_sequence/school_report_card.xml
odoo/addons/ssi_school/ir_sequence/school_student_score_sheet.xml
odoo/addons/ssi_school/models/__init__.py
odoo/addons/ssi_school/models/school_academic_term.py
odoo/addons/ssi_school/models/school_academic_year.py
odoo/addons/ssi_school/models/school_class.py
odoo/addons/ssi_school/models/school_curiculum.py
odoo/addons/ssi_school/models/school_curiculum_detail.py
odoo/addons/ssi_school/models/school_enrollment.py
odoo/addons/ssi_school/models/school_grade.py
odoo/addons/ssi_school/models/school_grade_type.py
odoo/addons/ssi_school/models/school_homeroom.py
odoo14_addon_ssi_school-14.0.2.0.0.dist-info/METADATA
odoo14_addon_ssi_school-14.0.2.0.0.dist-info/WHEEL
odoo14_addon_ssi_school-14.0.2.0.0.dist-info/top_level.txt
odoo14_addon_ssi_school-14.0.2.0.0.dist-info/RECORD
